MANIFEST.in
README.md
setup.py
decade/__init__.py
decade/client.py
decade/common.py
decade/localentry.py
decade/remoteentry.py
decade.egg-info/PKG-INFO
decade.egg-info/SOURCES.txt
decade.egg-info/dependency_links.txt
decade.egg-info/entry_points.txt
decade.egg-info/requires.txt
decade.egg-info/top_level.txt
decade/pycharm_config/deployment.xml
decade/pycharm_config/misc.xml
decade/pycharm_config/remote-mappings.xml
decade/pycharm_config/try.iml
decade/pycharm_config/webServers.xml
decade/pycharm_config/workspace.xml