Metadata-Version: 1.0
Name: decade
Version: 0.2.2
Summary: debug configurator sdk
Home-page: https://github.com/CarolineZhu/decade
Author: rzhu
Author-email: rzhu@splunk.com
License: Splunk Licence
Keywords: pip,decade,rzhu
Platform: any
